{
	"textures": [
		{
			"image": "ui.webp",
			"format": "RGBA8888",
			"size": {
				"w": 862,
				"h": 404
			},
			"scale": 1,
			"frames": [
				{
					"filename": "back",
					"rotated": false,
					"trimmed": false,
					"sourceSize": {
						"w": 128,
						"h": 128
					},
					"spriteSourceSize": {
						"x": 0,
						"y": 0,
						"w": 128,
						"h": 128
					},
					"frame": {
						"x": 603,
						"y": 1,
						"w": 128,
						"h": 128
					}
				},
				{
					"filename": "click",
					"rotated": false,
					"trimmed": false,
					"sourceSize": {
						"w": 128,
						"h": 128
					},
					"spriteSourceSize": {
						"x": 0,
						"y": 0,
						"w": 128,
						"h": 128
					},
					"frame": {
						"x": 603,
						"y": 131,
						"w": 128,
						"h": 128
					}
				},
				{
					"filename": "galaxy",
					"rotated": false,
					"trimmed": false,
					"sourceSize": {
						"w": 128,
						"h": 128
					},
					"spriteSourceSize": {
						"x": 0,
						"y": 0,
						"w": 128,
						"h": 128
					},
					"frame": {
						"x": 603,
						"y": 261,
						"w": 128,
						"h": 128
					}
				},
				{
					"filename": "play-again",
					"rotated": false,
					"trimmed": false,
					"sourceSize": {
						"w": 600,
						"h": 200
					},
					"spriteSourceSize": {
						"x": 0,
						"y": 0,
						"w": 600,
						"h": 200
					},
					"frame": {
						"x": 1,
						"y": 1,
						"w": 600,
						"h": 200
					}
				},
				{
					"filename": "play",
					"rotated": false,
					"trimmed": false,
					"sourceSize": {
						"w": 600,
						"h": 200
					},
					"spriteSourceSize": {
						"x": 0,
						"y": 0,
						"w": 600,
						"h": 200
					},
					"frame": {
						"x": 1,
						"y": 203,
						"w": 600,
						"h": 200
					}
				},
				{
					"filename": "sound-off",
					"rotated": false,
					"trimmed": false,
					"sourceSize": {
						"w": 128,
						"h": 128
					},
					"spriteSourceSize": {
						"x": 0,
						"y": 0,
						"w": 128,
						"h": 128
					},
					"frame": {
						"x": 733,
						"y": 1,
						"w": 128,
						"h": 128
					}
				},
				{
					"filename": "sound-on",
					"rotated": false,
					"trimmed": false,
					"sourceSize": {
						"w": 128,
						"h": 128
					},
					"spriteSourceSize": {
						"x": 0,
						"y": 0,
						"w": 128,
						"h": 128
					},
					"frame": {
						"x": 733,
						"y": 131,
						"w": 128,
						"h": 128
					}
				}
			]
		}
	],
	"meta": {
		"app": "https://www.codeandweb.com/texturepacker",
		"version": "3.0",
		"smartupdate": "$TexturePacker:SmartUpdate:0457a7798d4c6141c6bd4b1f14011ed3:4f82e44abf1e16f17d6bf5decfac9cb3:7056e196eac1c9ee9e017f5e80d26889$"
	}
}
